zensols/amr/resources/align.yml
zensols/amr/resources/annotate.conf
zensols/amr/resources/app.conf
zensols/amr/resources/coref.conf
zensols/amr/resources/default.conf
zensols/amr/resources/model.conf
zensols/amr/resources/obj.conf
zensols/amr/resources/obj.yml
zensols/amr/resources/score.yml
zensols/amr/resources/serial.conf
zensols/amr/resources/train.yml
zensols/amr/resources/model/inference.conf
zensols/amr/resources/model/model_generate_xfm_t5_base_wTT.json
zensols/amr/resources/model/model_generate_xfm_t5_large_wTT.json
zensols/amr/resources/model/model_parse_spring.json
zensols/amr/resources/model/model_parse_xfm_bart_base.json
zensols/amr/resources/model/model_parse_xfm_bart_large.json
zensols/amr/resources/model/model_parse_xfm_t5_base.json
zensols/amr/resources/model/model_parse_xfm_t5_large.json
zensols/amr/__init__.py
zensols/amr/align.py
zensols/amr/alignpop.py
zensols/amr/amrlib.py
zensols/amr/annotate.py
zensols/amr/app.py
zensols/amr/cli.py
zensols/amr/container.py
zensols/amr/coref.py
zensols/amr/corpprep.py
zensols/amr/doc.py
zensols/amr/docfac.py
zensols/amr/docparser.py
zensols/amr/domain.py
zensols/amr/dumper.py
zensols/amr/model.py
zensols/amr/score.py
zensols/amr/sent.py
zensols/amr/serial.py
zensols/amr/spacyadapt.py
zensols/amr/trainer.py
zensols/amr/tree.py
zensols/amr/varidx.py
zensols/amr/wlk/__init__.py
zensols/amr/wlk/amr_similarity.py
zensols/amr/wlk/graph_helpers.py
zensols/amr/wlk/score.py
zensols_amr-0.2.8.dist-info/METADATA
zensols_amr-0.2.8.dist-info/WHEEL
zensols_amr-0.2.8.dist-info/entry_points.txt
zensols_amr-0.2.8.dist-info/licenses/LICENSE.md
zensols_amr-0.2.8.dist-info/RECORD
