Metadata-Version: 2.3
Name: zensols_amr
Version: 0.2.8
Summary: Provides support for AMR graph manipulation, annotations and feature generation.
Project-URL: Homepage, https://github.com/plandes/amr
Project-URL: Documentation, https://plandes.github.io/amr
Project-URL: Repository, https://github.com/plandes/amr.git
Project-URL: Issues, https://github.com/plandes/amr/issues
Project-URL: Changelog, https://github.com/plandes/amr/blob/master/CHANGELOG.md
Author-email: Paul Landes <landes@mailc.net>
License: MIT
Keywords: abstract meaning representation,graph,semantics
Requires-Python: <3.13,>=3.11
Requires-Dist: amrlib~=0.8.0
Requires-Dist: cached-property~=1.5.2
Requires-Dist: graphviz~=0.20.1
Requires-Dist: networkx~=3.2.1
Requires-Dist: pandas
Requires-Dist: unidecode~=1.3.8
Requires-Dist: word2number==1.1
Requires-Dist: zensols-amr-coref~=0.0.2
Requires-Dist: zensols-install~=1.2.1
Requires-Dist: zensols-nlp~=1.12.8
